elements_api/__init__.py
elements_api/async_client.py
elements_api/async_interceptors.py
elements_api/elements_base_api.py
elements_api/sync_client.py
elements_api/models/__init__.py
elements_api/models/algorithm_computation_execution_pb2.py
elements_api/models/algorithm_computation_execution_pb2.pyi
elements_api/models/algorithm_computation_pb2.py
elements_api/models/algorithm_computation_pb2.pyi
elements_api/models/algorithm_config_pb2.py
elements_api/models/algorithm_config_pb2.pyi
elements_api/models/algorithm_manifest_pb2.py
elements_api/models/algorithm_manifest_pb2.pyi
elements_api/models/algorithm_pb2.py
elements_api/models/algorithm_pb2.pyi
elements_api/models/algorithm_version_pb2.py
elements_api/models/algorithm_version_pb2.pyi
elements_api/models/analysis_computation_pb2.py
elements_api/models/analysis_computation_pb2.pyi
elements_api/models/analysis_config_pb2.py
elements_api/models/analysis_config_pb2.pyi
elements_api/models/analysis_pb2.py
elements_api/models/analysis_pb2.pyi
elements_api/models/analysis_version_pb2.py
elements_api/models/analysis_version_pb2.pyi
elements_api/models/aoi_catalog_pb2.py
elements_api/models/aoi_catalog_pb2.pyi
elements_api/models/aoi_collection_pb2.py
elements_api/models/aoi_collection_pb2.pyi
elements_api/models/aoi_export_pb2.py
elements_api/models/aoi_export_pb2.pyi
elements_api/models/aoi_pb2.py
elements_api/models/aoi_pb2.pyi
elements_api/models/aoi_transaction_pb2.py
elements_api/models/aoi_transaction_pb2.pyi
elements_api/models/aoi_version_pb2.py
elements_api/models/aoi_version_pb2.pyi
elements_api/models/common_models_pb2.py
elements_api/models/common_models_pb2.pyi
elements_api/models/credit_pb2.py
elements_api/models/credit_pb2.pyi
elements_api/models/data_source_pb2.py
elements_api/models/data_source_pb2.pyi
elements_api/models/data_tracking_pb2.py
elements_api/models/data_tracking_pb2.pyi
elements_api/models/data_type_pb2.py
elements_api/models/data_type_pb2.pyi
elements_api/models/filter_pb2.py
elements_api-2026.1.91800.dist-info/licenses/LICENSE
elements_api-2026.1.91800.dist-info/METADATA
elements_api-2026.1.91800.dist-info/WHEEL
elements_api-2026.1.91800.dist-info/top_level.txt
elements_api-2026.1.91800.dist-info/RECORD
