Metadata-Version: 2.4
Name: elements-api
Version: 2026.1.91800
Summary: Elements API Client
License-File: LICENSE
Requires-Dist: grpcio
Requires-Dist: grpcio-status
Requires-Dist: requests
Dynamic: license-file
Dynamic: requires-dist
Dynamic: summary
